core/__init__.py
core/generate_annot.py
core/mp_handler.py
core/rhe.py
core/simulate_pheno.py
core/streaming_rhe.py
util/__init__.py
util/file_processing.py
util/logger.py
util/mat_mul.py
util/types.py
pyrhe-1.0.0.dist-info/METADATA
pyrhe-1.0.0.dist-info/WHEEL
pyrhe-1.0.0.dist-info/top_level.txt
pyrhe-1.0.0.dist-info/RECORD
