Metadata-Version: 2.1
Name: pyrhe
Version: 1.0.0
Summary: A Python package for Randomized Haseman-Elston regression for Multi-variance Components.
Author: Jiayi Ni
Author-email: nijiayi1119626@g.ucla.edu
Classifier: License :: OSI Approved :: MIT License
Requires-Python: >=3.8
Requires-Dist: bed-reader (==1.0.2)
Requires-Dist: numpy (>=1.23.1)
Requires-Dist: pandas (>=1.5.1)
Requires-Dist: python-dotenv (==1.0.1)
Requires-Dist: scipy (>=1.10.1)
Requires-Dist: tqdm (==4.65.0)
Requires-Dist: configparser (>=6.0.1)
